{
  "project_info": {
    "project_number": "850882059025",
    "project_id": "sl-chat-f994c",
    "storage_bucket": "sl-chat-f994c.appspot.com"
  },
  "client": [
    {
      "client_info": {
        "mobilesdk_app_id": "1:850882059025:android:afc089b9ec761cbf458ab0",
        "android_client_info": {
          "package_name": "com.example.sl_chat"
        }
      },
      "oauth_client": [],
      "api_key": [
        {
          "current_key": "AIzaSyCCECBLqUDvSpzLJVRDQo2mUcXjL2Qv0-U"
        }
      ],
      "services": {
        "appinvite_service": {
          "other_platform_oauth_client": []
        }
      }
    }
  ],
  "configuration_version": "1"
}